py_reflection/__init__.py
py_reflection/views.py
py_reflection-0.1.1.dist-info/LICENSE
py_reflection-0.1.1.dist-info/METADATA
py_reflection-0.1.1.dist-info/WHEEL
py_reflection-0.1.1.dist-info/top_level.txt
py_reflection-0.1.1.dist-info/RECORD
