Metadata-Version: 2.1
Name: py-reflection
Version: 0.1.1
Summary: Rest API endpoint to automate Microfocus Reflection Desktop Workspace
Home-page: https://github.com/prasun1060/py_reflection
Author: Prasun Bhattacharyya
Author-email: bhattacharyyaprasun47@gmail.com
License: UNKNOWN
Project-URL: Bug Tracker, https://github.com/prasun1060/py_reflection/issues
Platform: UNKNOWN
Classifier: Programming Language :: Python :: 3
Classifier: License :: OSI Approved :: BSD License
Classifier: Operating System :: OS Independent
Requires-Python: >=3.7
License-File: LICENSE
